PartSegData/__init__.py
PartSegData/fonts/Symbola.ttf
PartSegData/static_files/colors.npz
PartSegData/static_files/icons/configure.png
PartSegData/static_files/icons/document-open.png
PartSegData/static_files/icons/document-save-as.png
PartSegData/static_files/icons/draw-eraser.png
PartSegData/static_files/icons/draw-path.png
PartSegData/static_files/icons/icon.icns
PartSegData/static_files/icons/icon.ico
PartSegData/static_files/icons/icon.png
PartSegData/static_files/icons/icon_stack.png
PartSegData/static_files/icons/image-zoom-in.png
PartSegData/static_files/icons/task-accepted.png
PartSegData/static_files/icons/task-attempt.png
PartSegData/static_files/icons/task-reject.png
PartSegData/static_files/icons/transform-move.png
PartSegData/static_files/icons/transform-scale.png
PartSegData/static_files/icons/zoom-original.png
PartSegData/static_files/icons/zoom-select.png
PartSegData/static_files/icons/bigicons/configure.png
PartSegData/static_files/icons/bigicons/document-open.png
PartSegData/static_files/icons/bigicons/document-save-as.png
PartSegData/static_files/initial_images/one_nucleus.tiff
PartSegData/static_files/initial_images/stack.tif
PartSegData-0.10.0.dist-info/License.txt
PartSegData-0.10.0.dist-info/METADATA
PartSegData-0.10.0.dist-info/WHEEL
PartSegData-0.10.0.dist-info/top_level.txt
PartSegData-0.10.0.dist-info/RECORD
